[
{"rating": "7.5", "ratings_num": "22929", "year": "2016", "url": "https://movie.douban.com/subject/3868141/", "3_star": "33.0%", "1_star": "0.8%", "5_star": "20.6%", "img_url": "https://img3.doubanio.com/view/movie_poster_cover/lpst/public/p2403803540.jpg", "4_star": "40.3%", "imdb_id": "tt1473832", "2_star": "5.3%", "title": "单身日记：好孕来袭 Bridget Jones's Baby"},
{"rating": "7.4", "ratings_num": "79762", "year": "2016", "url": "https://movie.douban.com/subject/25894431/", "3_star": "34.1%", "1_star": "1.5%", "5_star": "17.2%", "img_url": "https://img5.doubanio.com/view/movie_poster_cover/lpst/public/p2403049086.jpg", "4_star": "41.8%", "imdb_id": "tt3748528", "2_star": "5.4%", "title": "星球大战外传：侠盗一号 Rogue One: A Star Wars Story"},
{"rating": "6.6", "ratings_num": "22386", "year": "2016", "url": "https://movie.douban.com/subject/26313740/", "3_star": "52.4%", "1_star": "1.4%", "5_star": "6.0%", "img_url": "https://img3.doubanio.com/view/movie_poster_cover/lpst/public/p2410038523.jpg", "4_star": "30.2%", "imdb_id": "tt3531824", "2_star": "10.0%", "title": "玩命直播 Nerve"},
{"rating": "4.6", "ratings_num": "1877", "year": "2016", "url": "https://movie.douban.com/subject/26388555/", "3_star": "23.7%", "1_star": "25.6%", "5_star": "5.1%", "img_url": "https://img1.doubanio.com/view/movie_poster_cover/lpst/public/p2405121017.jpg", "4_star": "8.5%", "imdb_id": "tt4884914", "2_star": "37.1%", "title": "一万公里的约定 一萬公里的約定"},
{"rating": "4.5", "ratings_num": "1735", "year": "2017", "url": "https://movie.douban.com/subject/26416774/", "3_star": "24.4%", "1_star": "41.9%", "5_star": "10.1%", "img_url": "https://img3.doubanio.com/view/movie_poster_cover/lpst/public/p2406829205.jpg", "4_star": "7.0%", "imdb_id": "tt6455336", "2_star": "16.7%", "title": "一路逆风"},
{"rating": "2.7", "ratings_num": "316", "year": "2017", "url": "https://movie.douban.com/subject/26865690/", "3_star": "0.0%", "1_star": "84.4%", "5_star": "6.3%", "img_url": "https://img3.doubanio.com/view/movie_poster_cover/lpst/public/p2406903891.jpg", "4_star": "0.0%", "imdb_id": "", "2_star": "9.4%", "title": "恐怖理发店"},
{"rating": "5.0", "ratings_num": "747", "year": "2017", "url": "https://movie.douban.com/subject/26912427/", "3_star": "30.1%", "1_star": "30.1%", "5_star": "13.3%", "img_url": "https://img3.doubanio.com/view/movie_poster_cover/lpst/public/p2410095594.jpg", "4_star": "6.0%", "imdb_id": "", "2_star": "20.5%", "title": "猪猪侠之英雄猪少年"},
{"rating": "7.0", "ratings_num": "64186", "year": "2016", "url": "https://movie.douban.com/subject/3434070/", "3_star": "42.6%", "1_star": "1.5%", "5_star": "11.8%", "img_url": "https://img5.doubanio.com/view/movie_poster_cover/lpst/public/p2410576676.jpg", "4_star": "35.6%", "imdb_id": "tt1355644", "2_star": "8.5%", "title": "太空旅客 Passengers"},
{"rating": "7.5", "ratings_num": "39876", "year": "2016", "url": "https://movie.douban.com/subject/26287884/", "3_star": "32.9%", "1_star": "0.7%", "5_star": "16.7%", "img_url": "https://img5.doubanio.com/view/movie_poster_cover/lpst/public/p2411608656.jpg", "4_star": "45.6%", "imdb_id": "tt4302938", "2_star": "4.1%", "title": "魔弦传说 Kubo and the Two Strings"},
{"rating": "7.9", "ratings_num": "45414", "year": "2015", "url": "https://movie.douban.com/subject/10484117/", "3_star": "21.1%", "1_star": "1.0%", "5_star": "23.2%", "img_url": "https://img3.doubanio.com/view/movie_poster_cover/lpst/public/p2411665175.jpg", "4_star": "52.2%", "imdb_id": "tt2057392", "2_star": "2.5%", "title": "天空之眼 Eye in the Sky"},
{"rating": "6.7", "ratings_num": "6016", "year": "2015", "url": "https://movie.douban.com/subject/25876760/", "3_star": "43.6%", "1_star": "2.3%", "5_star": "9.1%", "img_url": "https://img3.doubanio.com/view/movie_poster_cover/lpst/public/p2410887742.jpg", "4_star": "34.2%", "imdb_id": "tt5112400", "2_star": "10.7%", "title": "少年巴比伦"},
{"rating": "4.3", "ratings_num": "1748", "year": "2017", "url": "https://movie.douban.com/subject/26921827/", "3_star": "27.8%", "1_star": "33.1%", "5_star": "2.1%", "img_url": "https://img3.doubanio.com/view/movie_poster_cover/lpst/public/p2408893200.jpg", "4_star": "6.8%", "imdb_id": "", "2_star": "30.2%", "title": "大卫贝肯之倒霉特工熊"},
{"rating": "7.7", "ratings_num": "2425", "year": "2015", "url": "https://movie.douban.com/subject/26293468/", "3_star": "25.9%", "1_star": "1.2%", "5_star": "25.9%", "img_url": "https://img3.doubanio.com/view/movie_poster_cover/lpst/public/p2410472700.jpg", "4_star": "42.1%", "imdb_id": "tt5140556", "2_star": "5.0%", "title": "我的诗篇"},
{"rating": "7.8", "ratings_num": "125440", "year": "2016", "url": "https://movie.douban.com/subject/21324900/", "3_star": "24.3%", "1_star": "1.0%", "5_star": "23.7%", "img_url": "https://img3.doubanio.com/view/movie_poster_cover/lpst/public/p2411622421.jpg", "4_star": "47.5%", "imdb_id": "tt2543164", "2_star": "3.5%", "title": "降临 Arrival"},
{"rating": "4.2", "ratings_num": "1442", "year": "2015", "url": "https://movie.douban.com/subject/26617291/", "3_star": "29.8%", "1_star": "25.9%", "5_star": "0.4%", "img_url": "https://img3.doubanio.com/view/movie_poster_cover/lpst/public/p2409828702.jpg", "4_star": "2.4%", "imdb_id": "tt5500308", "2_star": "41.5%", "title": "心惊胆战 上身"},
{"rating": "8.8", "ratings_num": "243", "year": "2017", "url": "https://movie.douban.com/subject/26948106/", "3_star": "3.6%", "1_star": "3.6%", "5_star": "60.7%", "img_url": "https://img3.doubanio.com/view/movie_poster_cover/lpst/public/p2415244160.jpg", "4_star": "28.6%", "imdb_id": "", "2_star": "3.6%", "title": "缺失的爱"},
{"rating": "5.8", "ratings_num": "165929", "year": "2017", "url": "https://movie.douban.com/subject/25801066/", "3_star": "36.3%", "1_star": "12.9%", "5_star": "8.9%", "img_url": "https://img3.doubanio.com/view/movie_poster_cover/lpst/public/p2411953504.jpg", "4_star": "20.2%", "imdb_id": "tt5273624", "2_star": "21.6%", "title": "西游伏妖篇"},
{"rating": "6.5", "ratings_num": "6213", "year": "2017", "url": "https://movie.douban.com/subject/26831711/", "3_star": "38.5%", "1_star": "8.2%", "5_star": "11.6%", "img_url": "https://img3.doubanio.com/view/movie_poster_cover/lpst/public/p2414358483.jpg", "4_star": "30.5%", "imdb_id": "", "2_star": "11.3%", "title": "熊出没·奇幻空间"},
{"rating": "5.3", "ratings_num": "63852", "year": "2017", "url": "https://movie.douban.com/subject/26182910/", "3_star": "38.8%", "1_star": "15.2%", "5_star": "5.0%", "img_url": "https://img1.doubanio.com/view/movie_poster_cover/lpst/public/p2412371389.jpg", "4_star": "14.2%", "imdb_id": "tt4217392", "2_star": "26.9%", "title": "功夫瑜伽"},
{"rating": "6.9", "ratings_num": "9547", "year": "2017", "url": "https://movie.douban.com/subject/26717795/", "3_star": "37.6%", "1_star": "3.6%", "5_star": "11.0%", "img_url": "https://img3.doubanio.com/view/movie_poster_cover/lpst/public/p2412370372.jpg", "4_star": "38.0%", "imdb_id": "tt6461526", "2_star": "9.7%", "title": "健忘村"},
{"rating": "3.9", "ratings_num": "41364", "year": "2017", "url": "https://movie.douban.com/subject/26389696/", "3_star": "20.3%", "1_star": "43.8%", "5_star": "2.8%", "img_url": "https://img3.doubanio.com/view/movie_poster_cover/lpst/public/p2408307430.jpg", "4_star": "5.0%", "imdb_id": "tt6152908", "2_star": "28.1%", "title": "大闹天竺"},
{"rating": "7.0", "ratings_num": "177185", "year": "2017", "url": "https://movie.douban.com/subject/26862259/", "3_star": "36.1%", "1_star": "4.2%", "5_star": "14.5%", "img_url": "https://img1.doubanio.com/view/movie_poster_cover/lpst/public/p2408407697.jpg", "4_star": "36.7%", "imdb_id": "tt6461514", "2_star": "8.4%", "title": "乘风破浪"},
{"rating": "6.8", "ratings_num": "4166", "year": "2016", "url": "https://movie.douban.com/subject/26382767/", "3_star": "41.0%", "1_star": "2.9%", "5_star": "12.1%", "img_url": "https://img3.doubanio.com/view/movie_poster_cover/lpst/public/p2416009294.jpg", "4_star": "33.2%", "imdb_id": "tt2261287", "2_star": "10.8%", "title": "了不起的菲丽西 Ballerina"},
{"rating": "4.1", "ratings_num": "6952", "year": "2017", "url": "https://movie.douban.com/subject/26691509/", "3_star": "18.3%", "1_star": "39.4%", "5_star": "3.9%", "img_url": "https://img5.doubanio.com/view/movie_poster_cover/lpst/public/p2413341026.jpg", "4_star": "7.0%", "imdb_id": "", "2_star": "31.4%", "title": "东北往事之破马张飞"},
{"rating": "5.8", "ratings_num": "32396", "year": "2017", "url": "https://movie.douban.com/subject/3230115/", "3_star": "43.7%", "1_star": "8.4%", "5_star": "6.6%", "img_url": "https://img5.doubanio.com/view/movie_poster_cover/lpst/public/p2410569976.jpg", "4_star": "18.4%", "imdb_id": "tt1293847", "2_star": "22.9%", "title": "极限特工3：终极回归 xXx: The Return of Xander Cage"},
{"rating": "5.1", "ratings_num": "9185", "year": "2017", "url": "https://movie.douban.com/subject/26711487/", "3_star": "37.0%", "1_star": "16.5%", "5_star": "5.3%", "img_url": "https://img1.doubanio.com/view/movie_poster_cover/lpst/public/p2417948347.jpg", "4_star": "9.7%", "imdb_id": "tt6315750", "2_star": "31.4%", "title": "决战食神"},
{"rating": "5.0", "ratings_num": "2852", "year": "2017", "url": "https://movie.douban.com/subject/26745334/", "3_star": "19.4%", "1_star": "29.6%", "5_star": "10.3%", "img_url": "https://img1.doubanio.com/view/movie_poster_cover/lpst/public/p2422372719.jpg", "4_star": "14.6%", "imdb_id": "tt5992138", "2_star": "26.1%", "title": "游戏规则"},
{"rating": "8.6", "ratings_num": "125797", "year": "2016", "url": "https://movie.douban.com/subject/25934014/", "3_star": "13.4%", "1_star": "0.6%", "5_star": "48.0%", "img_url": "https://img3.doubanio.com/view/movie_poster_cover/lpst/public/p2425658570.jpg", "4_star": "36.2%", "imdb_id": "tt3783958", "2_star": "1.8%", "title": "爱乐之城 La La Land"},
{"rating": "5.2", "ratings_num": "1397", "year": "2017", "url": "https://movie.douban.com/subject/26425081/", "3_star": "31.1%", "1_star": "16.7%", "5_star": "7.0%", "img_url": "https://img3.doubanio.com/view/movie_poster_cover/lpst/public/p2403706134.jpg", "4_star": "11.2%", "imdb_id": "", "2_star": "33.9%", "title": "合约男女"},
{"rating": "3.5", "ratings_num": "1896", "year": "2017", "url": "https://movie.douban.com/subject/26815856/", "3_star": "11.3%", "1_star": "59.1%", "5_star": "5.4%", "img_url": "https://img1.doubanio.com/view/movie_poster_cover/lpst/public/p2426231159.jpg", "4_star": "3.0%", "imdb_id": "", "2_star": "21.2%", "title": "疯岳撬佳人"},
{"rating": "7.9", "ratings_num": "2637", "year": "2016", "url": "https://movie.douban.com/subject/26354572/", "3_star": "25.4%", "1_star": "0.3%", "5_star": "26.4%", "img_url": "https://img5.doubanio.com/view/movie_poster_cover/lpst/public/p2411622136.jpg", "4_star": "46.2%", "imdb_id": "tt3470600", "2_star": "1.8%", "title": "欢乐好声音 Sing"},
{"rating": "5.7", "ratings_num": "362", "year": "2016", "url": "https://movie.douban.com/subject/4078592/", "3_star": "30.8%", "1_star": "17.9%", "5_star": "15.4%", "img_url": "https://img1.doubanio.com/view/movie_poster_cover/lpst/public/p2426952758.jpg", "4_star": "12.8%", "imdb_id": "tt5482570", "2_star": "23.1%", "title": "上海王"}
]